gnucashreport/__init__.py
gnucashreport/buildreport.py
gnucashreport/cols.py
gnucashreport/financial.py
gnucashreport/formatreport.py
gnucashreport/gcreportcli.py
gnucashreport/gnucashbook.py
gnucashreport/margins.py
gnucashreport/rawdata.py
gnucashreport/report.py
gnucashreport/reportset.py
gnucashreport/utils.py
gnucashreport/xlsxreport.py
gnucashreport-0.2.5.dist-info/LICENSE.txt
gnucashreport-0.2.5.dist-info/METADATA
gnucashreport-0.2.5.dist-info/WHEEL
gnucashreport-0.2.5.dist-info/entry_points.txt
gnucashreport-0.2.5.dist-info/top_level.txt
gnucashreport-0.2.5.dist-info/RECORD
