Metadata-Version: 2.1
Name: gnucashreport
Version: 0.2.5
Summary: Reports from GnuCash to xlsx files
Home-page: https://github.com/partizand/gnucashreport
Author: Partizand
Author-email: UNKNOWN
License: GPLv3
Keywords: GnuCash,finance,reports
Platform: UNKNOWN
Classifier: Development Status :: 4 - Beta
Classifier: Programming Language :: Python :: 3
Classifier: Topic :: Office/Business :: Financial :: Accounting
Classifier: Topic :: Utilities
Classifier: Environment :: Console
Classifier: Operating System :: OS Independent
Classifier: License :: OSI Approved :: GNU General Public License v3 (GPLv3)
Requires-Dist: SQLAlchemy
Requires-Dist: numpy
Requires-Dist: pandas (>=0.23.0)
Requires-Dist: python-dateutil (>=2.7.3)
Requires-Dist: xlsxwriter (>=1.0.5)
